arithmetic_parsing/__init__.py
arithmetic_parsing/mathFuncs.py
arithmetic_parsing/examples/__init__.py
arithmetic_parsing/examples/assembly.py
arithmetic_parsing-0.0.1.post3.dist-info/METADATA
arithmetic_parsing-0.0.1.post3.dist-info/WHEEL
arithmetic_parsing-0.0.1.post3.dist-info/top_level.txt
arithmetic_parsing-0.0.1.post3.dist-info/RECORD
