Metadata-Version: 2.1
Name: arithmetic-parsing
Version: 0.0.1.post3
Summary: A simple, easy to use, arithmetic parsing tool with minimal dependencies
Home-page: https://github.com/wireboy5/arithmeticParsing
Author: Riley Wilton
Author-email: riley.j.wilton@gmail.com
License: UNKNOWN
Platform: UNKNOWN
Classifier: Programming Language :: Python :: 3
Classifier: License :: OSI Approved :: MIT License
Classifier: Operating System :: OS Independent
Requires-Python: >=3.9
